Workbook
Name Rubros: '9. Catálogos'!$A$2:$A$16
Name Lineas: '9. Catálogos'!$B$2:$B$9
Name Municipios: '9. Catálogos'!$C$2:$C$8
Name Unidades: '9. Catálogos'!$D$2:$D$16

Sheet 1. Instrucciones
A1: Plantilla de importación de proyectos — PRY-2026-002
B2: 2026.1
A4: Cómo diligenciar esta plantilla
A5: 1. No cambies los nombres de las hojas ni los encabezados de la fila 1.
A6: 2. Los códigos deben ser únicos dentro de cada hoja (3 a 6).
A7: 3. Usa punto y coma (;) para separar varias líneas estratégicas o municipios.
A8: 4. Las semanas van de 1 al total de semanas del proyecto.
A9: 5. Los montos aceptan formato colombiano (59.500.000 o 1.440.000,50).
A10: 6. Revisa la hoja 9. Catálogos para los valores permitidos.

Sheet 2. Proyecto
A1: Campo | B1: Valor
A2: Código | B2: PRY-2026-002
A3: Cliente | B3: Agencia de Cooperación Nórdica
A4: Líneas estratégicas | B4: LE02 - Emprendimiento; LE03 - Productividad
A5: Municipios | B5: Medellín (Antioquia); Barranquilla (Atlántico)
A6: Fecha de inicio | B6: 46300
A7: Fecha de fin | B7: 46416
A8: Valor total | B8: 177360000
A9: Meta de beneficiarios | B9: 500

Sheet 3. Objetivos
A1: Código | B1: Descripción
A2: O1 | B2: Formalizar bajo la figura jurídica idónea a las unidades productivas, estructurando un modelo de gobernanza, roles y operación técnica para el uso eficiente y compartido de la maquinaria.
A3: O2 | B3: Desarrollar el modelo de negocio, la planeación financiera y la identidad de marca de cada nodo asociativo, consolidando un portafolio de servicios B2B competitivo y herramientas de gestión administrativa básica
A4: O3 | B4: Implementar una estrategia de relacionamiento empresarial y posicionamiento comercial que facilite la generación de alianzas y oportunidades de mercado para las asociaciones.

Sheet 4. Actividades
A1: Código | B1: Código objetivo | C1: Nombre | D1: Semana inicio | E1: Semana fin | F1: Responsable (correo) | G1: Peso (opcional)
A2: A1.1 | B2: O1 | C2: Levantar información básica para la construcción de fichas de línea base de las asociaciones y de las unidades productivas participantes. | D2: 1 | E2: 1 | F2: coordinador@demo.muttuhub.local
A3: A1.2 | B3: O1 | C3: Desarrollar la jornada de visión compartida y diagnóstico del clima relacional. | D3: 2 | E3: 2 | F3: coordinador@demo.muttuhub.local
A4: A1.3 | B4: O1 | C4: Definir la arquitectura legal idónea para los nodos territoriales. | D4: 3 | E4: 3 | F4: coordinador@demo.muttuhub.local
A5: A1.4 | B5: O1 | C5: Gestionar la formalización jurídica y constitución legal de las asociaciones. | D5: 3 | E5: 6 | F5: coordinador@demo.muttuhub.local
A6: A1.5 | B6: O1 | C6: Co-diseñar el modelo de operación y gobernanza de la infraestructura compartida. | D6: 4 | E6: 5 | F6: coordinador@demo.muttuhub.local
A7: A1.6 | B7: O1 | C7: Dictar el taller de capacidades administrativas, contables y jurídicas bajo el enfoque "aprende haciendo". | D7: 6 | E7: 7 | F7: coordinador@demo.muttuhub.local
A8: A2.1 | B8: O2 | C8: Estructurar el modelo de negocio asociativo y la matriz de costos textiles. | D8: 2 | E8: 3 | F8: coordinador@demo.muttuhub.local
A9: A2.2 | B9: O2 | C9: Desarrollar la identidad visual, marca propia y marketing mix de los nodos. | D9: 4 | E9: 5 | F9: coordinador@demo.muttuhub.local
A10: A2.3 | B10: O2 | C10: Diseñar la estrategia de ventas y entrenar a los asociados en pitch comercial B2B. | D10: 6 | E10: 7 | F10: coordinador@demo.muttuhub.local
A11: A3.1 | B11: O3 | C11: Implementar una estrategia de relacionamiento empresarial y gestión de alianzas comerciales. | D11: 6 | E11: 16 | F11: coordinador@demo.muttuhub.local
A12: A3.2 | B12: O3 | C12: Gestionar la participación de las asociaciones en ferias comerciales departamentales o regionales. | D12: 11 | E12: 16 | F12: coordinador@demo.muttuhub.local
A13: A3.3 | B13: O3 | C13: Realizar el evento oficial de clausura, rendición de cuentas y certificación comunitaria del programa. | D13: 11 | E13: 12 | F13: coordinador@demo.muttuhub.local

Sheet 5. Entregables
A1: Código | B1: Código actividad | C1: Descripción | D1: Cantidad | E1: Unidad | F1: Tipo de medio exigido
A2: E1.1.1 | B2: A1.1 | C2: Memorias de eventos de socialización validadas | D2: 2 | E2: Memorias | F2: Memoria (PDF)
A3: E1.1.2 | B3: A1.1 | C3: Informe de línea base | D3: 1 | E3: Informe | F3: Informe (PDF)
A4: E1.2.1 | B4: A1.2 | C4: Mapas de expectativas y liderazgos consolidados | D4: 2 | E4: Mapas | F4: Documento (PDF)
A5: E1.3.1 | B5: A1.3 | C5: Actas de selección de la figura jurídica idónea suscritas por los asociados | D5: 2 | E5: Actas | F5: Acta firmada
A6: E1.4.1 | B6: A1.4 | C6: Estatutos asociativos aprobados | D6: 2 | E6: Estatutos | F6: Documento (PDF)
A7: E1.4.2 | B7: A1.4 | C7: RUT-NIT activos (DIAN) | D7: 2 | E7: RUT | F7: Certificado (PDF)
A8: E1.4.3 | B8: A1.4 | C8: Certificados de Existencia y Representación Legal (Cámara de Comercio) | D8: 2 | E8: Certificados | F8: Certificado (PDF)
A9: E1.5.1 | B9: A1.5 | C9: Manuales de operación y reglamentos de convivencia para el uso de la maquinaria del CedeTextil | D9: 2 | E9: Manuales | F9: Documento (PDF)
A10: E1.6.1 | B10: A1.6 | C10: Cartillas didácticas de gestión administrativa entregadas | D10: 2 | E10: Cartillas | F10: Documento (PDF)
A11: E1.6.2 | B11: A1.6 | C11: Registro de asociados entrenados | D11: 50 | E11: Asociados | F11: Listado de asistencia
A12: E2.1.1 | B12: A2.1 | C12: Modelos de negocio (Lean Canvas) y matrices financieras de costos y tarifas de maquila | D12: 2 | E12: Modelos de negocio | F12: Documento (PDF)
A13: E2.2.1 | B13: A2.2 | C13: Manuales de identidad visual corporativa (logos aplicados) | D13: 2 | E13: Manuales | F13: Documento (PDF)
... A21: E3.3.2 | B21: A3.3 | C21: Personas constituyentes de las asociaciones certificadas legalmente (100%) | D21: 100 | E21: % | F21: Listado de certificados

Sheet 6. Indicadores
A1: Código | B1: Código objetivo | C1: Nombre | D1: Meta | E1: Unidad | F1: Línea base
A2: IND-01 | B2: O1 | C2: Número de asociaciones constituidas legalmente | D2: 2 | E2: asociaciones
A3: IND-02 | B3: O2 | C3: Número de modelos de negocio consolidades | D3: 2 | E3: modelos de negocio
A4: IND-03 | B4: O2 | C4: Número de identidades de marca | D4: 2 | E4: identidades de marca
A5: IND-04 | B5: O3 | C5: Número de intenciones de compra | D5: 2 | E5: intenciones de compra

Sheet 7. Presupuesto
A1: Código rubro | B1: Rubro | C1: Valor asignado
A2: R01 | B2: Personal | C2: 59500000
A3: R02 | B3: Consultor | C3: 0
A4: R03 | B4: Subsidio arriendo | C4: 0
A5: R04 | B5: Promoción y divulgación | C5: 34000000
A6: R05 | B6: Alistamiento | C6: 0
A7: R06 | B7: Caracterización | C7: 1440000
A8: R07 | B8: Acompañamiento | C8: 0
A9: R08 | B9: Formación | C9: 45000000
A10: R09 | B10: Capital semilla | C10: 0
A11: R10 | B11: Viáticos | C11: 0
A12: R11 | B12: Varios | C12: 300000
A13: R12 | B13: Transporte | C13: 24000000
... A16: R15 | B16: Dotación | C16: 320000

Sheet 8. Programación
A1: Código rubro | B1: Rubro | C1: Mes 1 (2026-10) | D1: Mes 2 (2026-11) | E1: Mes 3 (2026-12) | F1: Mes 4 (2027-01) | G1: Total | H1: Control
A2: R01 | B2: Personal | C2: 14875000 | D2: 14875000 | E2: 14875000 | F2: 14875000 | G2: =SUM(C2:F2) -> 59500000 | H2: =G2-VLOOKUP(A2,'7. Presupuesto'!A:C,3,FALSE) -> 0
A3: R02 | B3: Consultor | G3: =SUM(C3:F3) -> 0 | H3: =G3-VLOOKUP(A3,'7. Presupuesto'!A:C,3,FALSE) -> 0
A4: R03 | B4: Subsidio arriendo | G4: =SUM(C4:F4) -> 0 | H4: =G4-VLOOKUP(A4,'7. Presupuesto'!A:C,3,FALSE) -> 0
A5: R04 | B5: Promoción y divulgación | C5: 8500000 | D5: 8500000 | E5: 8500000 | F5: 8500000 | G5: =SUM(C5:F5) -> 34000000 | H5: =G5-VLOOKUP(A5,'7. Presupuesto'!A:C,3,FALSE) -> 0
A6: R05 | B6: Alistamiento | G6: =SUM(C6:F6) -> 0 | H6: =G6-VLOOKUP(A6,'7. Presupuesto'!A:C,3,FALSE) -> 0
A7: R06 | B7: Caracterización | C7: 360000 | D7: 360000 | E7: 360000 | F7: 360000 | G7: =SUM(C7:F7) -> 1440000 | H7: =G7-VLOOKUP(A7,'7. Presupuesto'!A:C,3,FALSE) -> 0
A8: R07 | B8: Acompañamiento | G8: =SUM(C8:F8) -> 0 | H8: =G8-VLOOKUP(A8,'7. Presupuesto'!A:C,3,FALSE) -> 0
A9: R08 | B9: Formación | C9: 11250000 | D9: 11250000 | E9: 11250000 | F9: 11250000 | G9: =SUM(C9:F9) -> 45000000 | H9: =G9-VLOOKUP(A9,'7. Presupuesto'!A:C,3,FALSE) -> 0
A10: R09 | B10: Capital semilla | G10: =SUM(C10:F10) -> 0 | H10: =G10-VLOOKUP(A10,'7. Presupuesto'!A:C,3,FALSE) -> 0
A11: R10 | B11: Viáticos | G11: =SUM(C11:F11) -> 0 | H11: =G11-VLOOKUP(A11,'7. Presupuesto'!A:C,3,FALSE) -> 0
A12: R11 | B12: Varios | C12: 75000 | D12: 75000 | E12: 75000 | F12: 75000 | G12: =SUM(C12:F12) -> 300000 | H12: =G12-VLOOKUP(A12,'7. Presupuesto'!A:C,3,FALSE) -> 0
A13: R12 | B13: Transporte | C13: 6000000 | D13: 6000000 | E13: 6000000 | F13: 6000000 | G13: =SUM(C13:F13) -> 24000000 | H13: =G13-VLOOKUP(A13,'7. Presupuesto'!A:C,3,FALSE) -> 0
A14: R13 | B14: Suministros | C14: 3200000 | D14: 3200000 | E14: 3200000 | F14: 3200000 | G14: =SUM(C14:F14) -> 12800000 | H14: =G14-VLOOKUP(A14,'7. Presupuesto'!A:C,3,FALSE) -> 0
A15: R14 | B15: Oficina | G15: =SUM(C15:F15) -> 0 | H15: =G15-VLOOKUP(A15,'7. Presupuesto'!A:C,3,FALSE) -> 0
A16: R15 | B16: Dotación | C16: 80000 | D16: 80000 | E16: 80000 | F16: 80000 | G16: =SUM(C16:F16) -> 320000 | H16: =G16-VLOOKUP(A16,'7. Presupuesto'!A:C,3,FALSE) -> 0

Sheet 9. Catálogos
A1: Rubros | B1: Líneas estratégicas | C1: Municipios | D1: Unidades
A2: R01 | B2: LE01 - Empleabilidad | C2: Medellín (Antioquia) | D2: Personas
A3: R02 | B3: LE02 - Emprendimiento | C3: Barranquilla (Atlántico) | D3: Unidades
A4: R03 | B4: LE03 - Productividad | C4: Bogotá D.C. (Bogotá D.C.) | D4: Informe
A5: R04 | B5: LE04 - Cultural | C5: Cartagena de Indias (Bolívar) | D5: Memoria
A6: R05 | B6: LE05 - Social | C6: Manizales (Caldas) | D6: Mapa
A7: R06 | B7: LE06 - Cívico-político | C7: Bucaramanga (Santander) | D7: Acta
A8: R07 | B8: LE07 - Método Muttu | C8: Cali (Valle del Cauca) | D8: Estatuto
A9: R08 | B9: LE08 - Ambiental | D9: Certificado
A10: R09 | D10: RUT
A11: R10 | D11: Documento
A12: R11 | D12: Registro
A13: R12 | D13: Kit
A14: R13 | D14: Taller
A15: R14 | D15: Jornada
A16: R15 | D16: Servicio
